pimpmydb/__init__.py
pimpmydb/columns/__init__.py
pimpmydb/columns/column.py
pimpmydb/columns/double_column.py
pimpmydb/columns/int_column.py
pimpmydb/columns/text_column.py
pimpmydb/columns/timestamp_column.py
pimpmydb/columns/varchar_column.py
pimpmydb/database/__init__.py
pimpmydb/database/database.py
pimpmydb/fields/__init__.py
pimpmydb/fields/email_field.py
pimpmydb/fields/field.py
pimpmydb/fields/number_field.py
pimpmydb/fields/text_field.py
pimpmydb/forms/__init__.py
pimpmydb/forms/form.py
pimpmydb/query_generator/__init__.py
pimpmydb/query_generator/query_generator.py
pimpmydb/statement_generator/__init__.py
pimpmydb/statement_generator/statement_generator.py
pimpmydb/tables/__init__.py
pimpmydb/tables/table.py
pimpmydb-0.0.16.dev1.dist-info/LICENSE
pimpmydb-0.0.16.dev1.dist-info/METADATA
pimpmydb-0.0.16.dev1.dist-info/WHEEL
pimpmydb-0.0.16.dev1.dist-info/top_level.txt
pimpmydb-0.0.16.dev1.dist-info/zip-safe
pimpmydb-0.0.16.dev1.dist-info/RECORD
