Metadata-Version: 2.1
Name: pimpmydb
Version: 0.0.16.dev1
Summary: "An easy to use database utility for creating and managing a MySQL database."
Home-page: https://github.com/gurgy11/pimpmydb
Author: Gregory Bockus
Author-email: "gregory.bockus@gmail.com"
License: UNKNOWN
Project-URL: Bug Tracker, https://github.com/gurgy11/pimpmydb/issues
Platform: UNKNOWN
Classifier: Programming Language :: Python :: 3
Classifier: License :: OSI Approved :: MIT License
Classifier: Operating System :: OS Independent
Requires-Python: >=3.6
Requires-Dist: mysql-connector-python
Requires-Dist: python-dotenv
